Workbook

Sheet Reformulated IS
A1: Rheinmetall AG — Reformulated Income Statement
A2: € million | IFRS | Fiscal year ended 31 December | External / internal cost lens
A3: 2025 and 2024 use the 2025 Annual Report (2024 restated for IFRS 5); 2023 is as reported in the 2024 Annual Report and is not restated for the 2025 civilian-business discontinuation.
A5: REFORMULATED INCOME STATEMENT
A6: Line item | B6: 2025 (€m) | C6: 2024 Restated (€m) | D6: 2023 As reported (€m) | E6: Status | F6: Primary source | G6: Calculation / classification | H6: Notes
A7: Sales | B7: =B62 -> 9935 | C7: =C62 -> 7715 | D7: =D62 -> 7176 | E7: CHECK / AGENT | F7: Reported inputs below | G7: Linked to reported Sales
A8: Changes in inventories and own work capitalised | B8: =B63 -> 521 | C8: =C63 -> 132 | D8: =D63 -> 696 | E8: CHECK / AGENT | F8: Reported inputs below | G8: Linked to reported inventory change + own work capitalised
A9: Value of Production | B9: =SUM(B7:B8) -> 10456 | C9: =SUM(C7:C8) -> 7847 | D9: =SUM(D7:D8) -> 7872 | E9: AGENT | F9: Calculation | G9: Sales + changes in inventories / own work
A10: Cost of materials | B10: =B65 -> -5252 | C10: =C65 -> -3693 | D10: =D65 -> -3935 | E10: CHECK / AGENT | F10: Reported inputs below | G10: Reported operating cost
A11: Other operating expenses (recurring) | B11: =B68-B45-B48 -> -1103 | C11: =C68-C45-C48 -> -864 | D11: =D68-D45-D48 -> -881 | E11: AGENT | F11: Notes 15 / acquisition note | G11: Reported Opex less disclosed unusual disposal losses and M&A costs
A12: Other operating income (recurring) | B12: =B64-SUM(B42:B44)-B47 -> 110 | C12: =C64-SUM(C42:C44)-C47 -> 98 | D12: =D64-SUM(D42:D44)-D47 -> 93 | E12: AGENT | F12: Note 11 | G12: Reported OI less refunds, provision reversals, disposal gains and asset reversals
A13: Added Value | B13: =SUM(B9:B12) -> 4211 | C13: =SUM(C9:C12) -> 3388 | D13: =SUM(D9:D12) -> 3149 | E13: AGENT | F13: Calculation | G13: Value of Production + materials + recurring Opex + recurring OI
A14: Personnel expenses | B14: =B66 -> -2314 | C14: =C66 -> -1844 | D14: =D66 -> -2047 | E14: CHECK / AGENT | F14: Reported inputs below | G14: Reported personnel expense
A15: EBITDA | B15: =SUM(B13:B14) -> 1897 | C15: =SUM(C13:C14) -> 1544 | D15: =SUM(D13:D14) -> 1102 | E15: AGENT | F15: Calculation | G15: Added Value + personnel expense
A16: Amortization & depreciation (excl. impairment) | B16: =B67-B46 -> -389 | C16: =C67-C46 -> -284 | D16: =D67-D46 -> -302 | E16: AGENT | F16: Note 14 | G16: Reported D&A / impairment less impairment
A17: Restructuring costs removed | B17: =-B53 -> 7 | C17: =-C53 -> 2 | D17: =-D53 -> 1 | E17: AGENT | F17: CMR special-item reconciliation | G17: Add-back because original expense line is not disclosed
A18: Core Operating Income | B18: =SUM(B15:B17) -> 1515 | C18: =SUM(C15:C17) -> 1262 | D18: =SUM(D15:D17) -> 801 | E18: AGENT | F18: Calculation | G18: EBITDA + recurring D&A + restructuring add-back
A19: Result from equity-method investments (recurring) | B19: =B69-B49-B51-B52 -> 1 | C19: =C69-C49-C51-C52 -> -33 | D19: =D69-D49-D51-D52 -> 4 | E19: AGENT | F19: Note 22 | G19: Reported at-equity result less disclosed disposal / remeasurement gains
A20: Other financial result (recurring, non-interest) | B20: =B70-B50 -> -22 | C20: =C70-C50 -> -9 | D20: =D70-D50 -> -6 | E20: AGENT | F20: Note 7 / reported financial result | G20: Reported other financial result less blackned step-up gain
A21: Non-core Operating Income | B21: =SUM(B19:B20) -> -21 | C21: =SUM(C19:C20) -> -42 | D21: =SUM(D19:D20) -> -2 | E21: AGENT | F21: Calculation | G21: Recurring at-equity result + recurring other financial result
A22: Operating Income | B22: =B18+B21 -> 1494 | C22: =C18+C21 -> 1220 | D22: =D18+D21 -> 799 | E22: AGENT | F22: Calculation | G22: Core + non-core operating income
A23: Interest income | B23: =B71 -> 4 | C23: =C71 -> 14 | D23: =D71 -> 29 | E23: CHECK / AGENT | F23: Reported inputs below | G23: Interest income
A24: Interest expense | B24: =B72 -> -116 | C24: =C72 -> -116 | D24: =D72 -> -111 | E24: CHECK / AGENT | F24: Reported inputs below | G24: Interest expense
A25: Net financial result | B25: =SUM(B23:B24) -> -112 | C25: =SUM(C23:C24) -> -102 | D25: =SUM(D23:D24) -> -82 | E25: AGENT | F25: Calculation | G25: Interest income + interest expense
A26: Income before unusual items and taxes | B26: =B22+B25 -> 1382 | C26: =C22+C25 -> 1118 | D26: =D22+D25 -> 717 | E26: AGENT | F26: Calculation | G26: Operating Income + net financial result
A27: Unusual items | B27: =B58 -> -136 | C27: =C58 -> 271 | D27: =D58 -> 51 | E27: AGENT | F27: Unusual-item schedule | G27: Linked to total unusual items
A28: Income before taxes (comprehensive-income bridge subtotal) | B28: =SUM(B26:B27) -> 1246 | C28: =SUM(C26:C27) -> 1389 | D28: =SUM(D26:D27) -> 768 | E28: AGENT | F28: Calculation | G28: Income before unusual items and taxes + unusual items | H28: Includes tax-only and OCI unusual items per the reformulation method.
A29: Income taxes — recurring continuing operations | B29: =-B73-B54-B55 -> -395 | C29: =-C73-C54-C55 -> -327 | D29: =-D73-D54-D55 -> -188 | E29: AGENT | F29: Tax notes | G29: − reported continuing tax expense − signed prior-period tax effect − signed rate-change effect
A30: Income taxes — discontinued operations | B30: =B74 -> -27 | C30: =C74 -> -14 | D30: =D74 -> 15 | E30: AGENT | F30: Discontinued-operations notes | G30: Signed tax effect from discontinued operations
A31: Tax on OCI | B31: =B75 -> -38 | C31: =C75 -> -47 | D31: =D75 -> 2 | E31: AGENT | F31: OCI tax note | G31: Signed tax on OCI
A32: Total income taxes | B32: =SUM(B29:B31) -> -460 | C32: =SUM(C29:C31) -> -388 | D32: =SUM(D29:D31) -> -171 | E32: AGENT | F32: Calculation | G32: Sum of recurring continuing tax + discontinued tax + OCI tax
A33: Rounding / reconciliation | B33: =B76-(B28+B32) -> 0 | C33: =C76-(C28+C32) -> -2 | D33: =D76-(D28+D32) -> 0 | E33: AGENT | F33: Calculation | G33: Reported comprehensive income less bridge subtotal and total tax | H33: Source / note rounding residual.
A34: Total comprehensive income | B34: =B28+B32+B33 -> 786 | C34: =C28+C32+C33 -> 999 | D34: =D28+D32+D33 -> 597 | E34: AGENT | F34: Calculation / reported check | G34: Bridge subtotal + total tax + rounding
A35: of which: non-controlling interests | B35: =B77 -> 150 | C35: =C77 -> 98 | D35: =D77 -> 39 | E35: CHECK / AGENT | F35: Reported comprehensive income | G35: Reported NCI split
A36: of which: Rheinmetall AG shareholders | B36: =B78 -> 636 | C36: =C78 -> 901 | D36: =D78 -> 558 | E36: CHECK / AGENT | F36: Reported comprehensive income | G36: Reported parent split
A40: UNUSUAL ITEMS SUPPORTING SCHEDULE
A41: Item | B41: 2025 (€m) | C41: 2024 Restated (€m) | D41: 2023 As reported (€m) | E41: Type | F41: Original line | G41: Criterion | H41: Primary source
A42: Refunds / insurance recoveries | B42: 118 | C42: 21 | D42: 5 | E42: Pre-tax | F42: Other operating income | G42: (a) refunds / insurance recoveries | H42: AR 2025 Note 11 p.219; AR 2024 Note 11 p.206
A43: Reversal of provisions | B43: 44 | C43: 55 | D43: 53 | E43: Pre-tax | F43: Other operating income | G43: (b) reversal of provisions | H43: AR 2025 Note 11 p.219; AR 2024 Note 11 p.206
A44: Disposal gains — fixed assets / divestments | B44: 1 | C44: 2 | D44: 0 | E44: Pre-tax | F44: Other operating income | G44: (c) disposal gains | H44: AR 2025 Note 11 p.219; AR 2024 Note 11 p.206
A45: Disposal losses — non-current assets | B45: -9 | C45: -21 | D45: -8 | E45: Pre-tax | F45: Other operating expenses | G45: (c) disposal losses | H45: AR 2025 Note 15 p.220; AR 2024 Note 15 p.208
A46: Impairment losses | B46: -17 | C46: 0 | D46: -6 | E46: Pre-tax | F46: D&A / impairment | G46: (d) impairment | H46: AR 2025 Note 14 p.220; AR 2024 Note 14 p.208
A47: Reversal of non-financial assets | B47: 0 | C47: 2 | D47: 2 | E47: Pre-tax | F47: Other operating income | G47: (d) impairment reversal | H47: AR 2025 Note 11 p.219; AR 2024 Note 11 p.206
A48: Acquisition-related transaction costs — Loc Performance | B48: 0 | C48: -6 | D48: 0 | E48: Pre-tax | F48: Other operating expenses | G48: (e) M&A transaction costs | H48: AR 2024 Note 7 p.203
A49: Gain on sale of AIM stake | B49: 46 | C49: 0 | D49: 0 | E49: Pre-tax | F49: Equity-method result | G49: (g) disposal gain on investment | H49: AR 2025 Note 22 p.230
A50: Remeasurement gain on previously held blackned stake | B50: 15 | C50: 0 | D50: 0 | E50: Pre-tax | F50: Other financial result | G50: (g) step-up / fair-value gain | H50: AR 2025 Note 7 p.214
A51: Shriram share disposal gain | B51: 0 | C51: 0 | D51: 31 | E51: Pre-tax | F51: Equity-method result | G51: (g) disposal gain on investment | H51: AR 2024 Note 22 p.216
A52: Shriram initial fair-value remeasurement | B52: 0 | C52: 0 | D52: 22 | E52: Pre-tax | F52: Equity-method result | G52: (g) fair-value remeasurement | H52: AR 2024 Note 22 p.216
A53: Restructuring costs | B53: -7 | C53: -2 | D53: -1 | E53: Pre-tax | F53: Line not disclosed; lowest certain level | G53: (f) restructuring | H53: AR 2025 CMR p.55; AR 2024 CMR p.52
... A57: Other comprehensive income, pre-tax | B57: -11 | C57: 238 | D57: 9 | E57: OCI | F57: Other comprehensive income | G57: (j) OCI pre-tax | H57: AR 2025 Note 26 p.234; AR 2024 Note 26 p.221
A58: Total unusual items | B58: =SUM(B42:B57) -> -136 | C58: =SUM(C42:C57) -> 271 | D58: =SUM(D42:D57) -> 51 | E58: Formula | G58: Vertical sum of unusual-item schedule
A60: REPORTED SOURCE INPUTS
A61: Reported line / input | B61: 2025 (€m) | C61: 2024 Restated (€m) | D61: 2023 As reported (€m) | E61: Status | F61: Primary source | G61: Use | H61: Notes
A62: Sales | B62: 9935 | C62: 7715 | D62: 7176 | E62: CHECK / AGENT | F62: AR 2025 p.199; AR 2024 p.188 | G62: Main statement
A63: Changes in inventories and own work capitalised | B63: 521 | C63: 132 | D63: 696 | E63: CHECK / AGENT | F63: AR 2025 p.199; AR 2024 p.188 | G63: Main statement
A64: Other operating income | B64: 273 | C64: 178 | D64: 153 | E64: CHECK / AGENT | F64: AR 2025 Note 11 p.219; AR 2024 Note 11 p.206 | G64: Recurring OI bridge
A65: Cost of materials | B65: -5252 | C65: -3693 | D65: -3935 | E65: CHECK / AGENT | F65: AR 2025 p.199 / Note 12; AR 2024 p.188 | G65: Main statement
A66: Personnel expenses | B66: -2314 | C66: -1844 | D66: -2047 | E66: CHECK / AGENT | F66: AR 2025 p.199 / Note 13; AR 2024 p.188 | G66: Main statement
A67: Amortization, depreciation and impairment | B67: -406 | C67: -284 | D67: -308 | E67: CHECK / AGENT | F67: AR 2025 p.199 / Note 14 p.220; AR 2024 p.188 / Note 14 p.208 | G67: Recurring D&A bridge
A68: Other operating expenses | B68: -1112 | C68: -891 | D68: -889 | E68: CHECK / AGENT | F68: AR 2025 p.199 / Note 15 p.220; AR 2024 p.188 / Note 15 p.208 | G68: Recurring Opex bridge
A69: Result from investments accounted for using equity method | B69: 47 | C69: -33 | D69: 57 | E69: CHECK / AGENT | F69: AR 2025 p.199 / Note 22 p.230; AR 2024 p.188 / Note 22 p.216 | G69: Non-core bridge
A70: Other financial result | B70: -7 | C70: -9 | D70: -6 | E70: CHECK / AGENT | F70: AR 2025 p.199; AR 2024 p.188 | G70: Non-core bridge
A71: Interest income | B71: 4 | C71: 14 | D71: 29 | E71: CHECK / AGENT | F71: AR 2025 p.199; AR 2024 p.188 | G71: Net financial result
A72: Interest expense | B72: -116 | C72: -116 | D72: -111 | E72: CHECK / AGENT | F72: AR 2025 p.199; AR 2024 p.188 | G72: Net financial result
A73: Continuing income tax expense (positive magnitude) | B73: 396 | C73: 328 | D73: 185 | E73: CHECK / AGENT | F73: AR 2025 Note 16 pp.220–221; AR 2024 Note 16 p.208 | G73: Tax bridge
A74: Discontinued-operations tax effect (signed) | B74: -27 | C74: -14 | D74: 15 | E74: AGENT | F74: AR 2025 Note 8 pp.215–217; AR 2024 Note 8 p.204 | G74: Tax bridge | H74: 2025/2024 aggregate civilian + pistons tax effects
A75: OCI tax effect (signed) | B75: -38 | C75: -47 | D75: 2 | E75: AGENT | F75: AR 2025 Note 26 p.234; AR 2024 Note 26 p.221 | G75: Tax bridge
A76: Total comprehensive income | B76: 786 | C76: 999 | D76: 597 | E76: CHECK / AGENT | F76: AR 2025 p.199; AR 2024 p.188 | G76: Reconciliation target
A77: NCI comprehensive income | B77: 150 | C77: 98 | D77: 39 | E77: CHECK / AGENT | F77: AR 2025 p.199; AR 2024 p.188 | G77: Reported split
A78: Parent comprehensive income | B78: 636 | C78: 901 | D78: 558 | E78: CHECK / AGENT | F78: AR 2025 p.199; AR 2024 p.188 | G78: Reported split
A79: Reported EBT (check only) | B79: 1572 | C79: 1168 | D79: 815 | E79: CHECK / AGENT | F79: AR 2025 p.199; AR 2024 p.188 | G79: Check only
A80: Reported earnings after taxes (check only) | B80: 835 | C80: 808 | D80: 586 | E80: CHECK / AGENT | F80: AR 2025 p.199; AR 2024 p.188 | G80: Check only
A82: Scope / source note
A83: Figures are in € million. 2025 and 2024 are continuing-operations figures from the 2025 Annual Report, with 2024 restated under IFRS 5. The 2023 column is from the 2024 Annual Report and retains the then-reported continuing-operations scope (including Power Systems), so it is not directly comparable with 2025/2024. Unusual items follow the supplied reformulation methodology and are linked once into the comprehensive-income bridge.

Sheet Managerial BS
A1: Rheinmetall AG — Managerial Balance Sheet
A2: € million | IFRS | Closing balances at 31 December | Consolidated incl. NCI
A3: 2025 and 2024 source balances are from the 2025 Annual Report; 2023 is from the 2024 Annual Report. The 2024 balance sheet is not restated for the 2025 IFRS 5 civilian-business discontinuation, so it is not fully scope-matched to the 2024 restated continuing-operations income statement. No unsupported 2024 disposal-group balance-sheet estimate is made.
A5: MANAGERIAL BALANCE SHEET
A6: Category | B6: 2025 (€m) | C6: 2024 (€m) | D6: 2023 (€m) | E6: Status | F6: Source / calculation | G6: Classification
A7: CURRENT OPERATING ASSETS
A8: Inventories | B8: 4721 | C8: 3989 | D8: 3244 | E8: 2025/24 CHECK; 2023 AGENT | F8: AR 2025 p.200 / Note 23 p.229; AR 2024 p.189 / Note 23 p.217 | G8: Operating; inventories include prepayments made.
A9: Contract assets | B9: 957 | C9: 692 | D9: 516 | E9: 2025/24 CHECK; 2023 AGENT | F9: AR 2025 p.200; AR 2024 p.189 | G9: Operating contract asset.
A10: Trade receivables | B10: 1907 | C10: 1959 | D10: 2021 | E10: 2025/24 CHECK; 2023 AGENT | F10: AR 2025 p.200; AR 2024 p.189 | G10: Operating receivable.
A11: Contract acquisition costs | B11: 122 | C11: 139 | D11: 93 | E11: AGENT | F11: AR 2025 Note 24 p.230; AR 2024 Note 24 p.217 | G11: Operating non-financial asset; included irrespective of IAS 1 maturity.
A12: Contract costs | B12: 76 | C12: 44 | D12: 41 | E12: AGENT | F12: AR 2025 Note 24 p.230; AR 2024 Note 24 p.217 | G12: Operating non-financial asset; included irrespective of IAS 1 maturity.
A13: Prepaid expenses | B13: 78 | C13: 80 | D13: 67 | E13: AGENT | F13: AR 2025 Note 24 p.230; AR 2024 Note 24 p.217 | G13: Operating non-financial asset.
A14: Other non-financial operating assets | B14: 59 | C14: 80 | D14: 60 | E14: AGENT | F14: AR 2025 Note 24 p.230; AR 2024 Note 24 p.217 | G14: Excludes other-tax receivables and pension surplus; 2024/23 combines subsidy, insurance and other non-financial rows.
A15: Derivative assets — operating-risk hedges | B15: 80 | C15: 41 | D15: 25 | E15: 2025/24 CHECK; 2023 AGENT | F15: AR 2025 Note 24 p.230 & Note 34 pp.248–249; AR 2024 Note 24 p.217 / Note 34 p.233 | G15: Operating; all maturities. Derivatives are disclosed as currency/commodity hedges.
A16: Current operating assets | B16: =SUM(B8:B15) -> 8000 | C16: =SUM(C8:C15) -> 7024 | D16: =SUM(D8:D15) -> 6067 | E16: CHECK / AGENT | F16: Sum of operating-asset lines above | G16: Managerial current operating assets.
A18: OPERATING LIABILITIES
A19: Contract liabilities | B19: 5642 | C19: 3866 | D19: 2594 | E19: 2025/24 CHECK; 2023 AGENT | F19: AR 2025 p.200; AR 2024 p.189 | G19: Operating liability.
A20: Trade liabilities | B20: 1186 | C20: 1151 | D20: 1222 | E20: 2025/24 CHECK; 2023 AGENT | F20: AR 2025 p.200; AR 2024 p.189 | G20: Operating liability.
A21: Other current provisions | B21: 891 | C21: 807 | D21: 690 | E21: 2025/24 CHECK; 2023 AGENT | F21: AR 2025 p.200 / Note 28 p.240; AR 2024 p.189 / Note 28 p.226 | G21: Operating provisions.
A22: Pension provisions | B22: 278 | C22: 527 | D22: 562 | E22: AGENT | F22: AR 2025 p.200; AR 2024 p.189 | G22: Operating pension obligation before plan surplus.
A23: Less: net defined-benefit asset / plan surplus | B23: -289 | C23: -275 | D23: -99 | E23: AGENT | F23: AR 2025 Note 24 p.230; AR 2024 Note 24 p.217 | G23: Netted against pension provisions under the method.
A24: Pension provisions, net of plan surplus | B24: =B22+B23 -> -11 | C24: =C22+C23 -> 252 | D24: =D22+D23 -> 463 | E24: CHECK / AGENT | F24: Pension provisions less plan surplus | G24: Operating liability; may be negative when plan surplus exceeds provision.
A25: Other non-current provisions | B25: 280 | C25: 285 | D25: 230 | E25: 2025/24 CHECK; 2023 AGENT | F25: AR 2025 p.200 / Note 28 p.240; AR 2024 p.189 / Note 28 p.226 | G25: Operating provisions regardless of maturity.
A26: Social-security liabilities | B26: 11 | C26: 14 | D26: 14 | E26: AGENT | F26: AR 2025 Note 30 p.243; AR 2024 Note 30 p.230 | G26: Operating non-financial liability.
A27: Other non-financial liabilities | B27: 89 | C27: 130 | D27: 77 | E27: AGENT | F27: AR 2025 Note 30 p.243; AR 2024 Note 30 p.230 | G27: Operating non-financial liability; excludes other-tax liabilities.
A28: Derivative liabilities — operating-risk hedges | B28: 20 | C28: 22 | D28: 24 | E28: 2025/24 CHECK; 2023 AGENT | F28: AR 2025 Note 30 p.243 & Note 34 pp.248–249; AR 2024 Note 30 p.230 / Note 34 p.233 | G28: Operating; all maturities. Currency/commodity hedges.
A29: Operating liabilities | B29: =SUM(B19:B21)+B24+SUM(B25:B28) -> 8108 | C29: =SUM(C19:C21)+C24+SUM(C25:C28) -> 6527 | D29: =SUM(D19:D21)+D24+SUM(D25:D28) -> 5314 | E29: CHECK / AGENT | F29: Contract/trade/provisions/pensions/non-financial liabilities/operating derivatives | G29: Recurring operating liabilities.
A30: Net operating working capital (NOWC) | B30: =B16-B29 -> -108 | C30: =C16-C29 -> 497 | D30: =D16-D29 -> 753 | E30: CHECK / AGENT | F30: Current operating assets − operating liabilities | G30: Closing-balance NOWC.
A32: NON-CURRENT OPERATING ASSETS
A33: Goodwill | B33: 1354 | C33: 1426 | D33: 1125 | E33: 2025/24 CHECK; 2023 AGENT | F33: AR 2025 p.200; AR 2024 p.189 | G33: Non-current operating asset.
A34: Other intangible assets | B34: 1244 | C34: 1376 | D34: 952 | E34: 2025/24 CHECK; 2023 AGENT | F34: AR 2025 p.200; AR 2024 p.189 | G34: Non-current operating asset.
A35: Right-of-use assets | B35: 338 | C35: 334 | D35: 271 | E35: 2025/24 CHECK; 2023 AGENT | F35: AR 2025 p.200; AR 2024 p.189 | G35: Non-current operating asset.
A36: Property, plant and equipment | B36: 1962 | C36: 1853 | D36: 1370 | E36: 2025/24 CHECK; 2023 AGENT | F36: AR 2025 p.200; AR 2024 p.189 | G36: Non-current operating asset.
A37: Investment property | B37: 2 | C37: 20 | D37: 22 | E37: 2025/24 CHECK; 2023 AGENT | F37: AR 2025 p.200; AR 2024 p.189 | G37: Operating by default under supplied methodology.
A38: Non-current operating assets | B38: =SUM(B33:B37) -> 4900 | C38: =SUM(C33:C37) -> 5009 | D38: =SUM(D33:D37) -> 3740 | E38: CHECK / AGENT | F38: Sum of non-current operating assets | G38: Managerial non-current operating assets.
A39: Gross operating invested capital | B39: =B16+B38 -> 12900 | C39: =C16+C38 -> 12033 | D39: =D16+D38 -> 9807 | E39: CHECK / AGENT | F39: Current operating assets + non-current operating assets | G39: Gross means before operating liabilities, not before depreciation.
A40: Net operating invested capital | B40: =B39-B29 -> 4792 | C40: =C39-C29 -> 5506 | D40: =D39-D29 -> 4493 | E40: CHECK / AGENT | F40: Gross operating invested capital − operating liabilities | G40: Operating capital net of recurring operating liabilities.
A42: NON-OPERATING ASSETS
A43: Investments accounted for using the equity method | B43: 213 | C43: 346 | D43: 373 | E43: 2025/24 CHECK; 2023 AGENT | F43: AR 2025 p.200; AR 2024 p.189 | G43: Non-operating asset; associated income is non-core operating income.
A44: Assets held for sale, net of associated liabilities | B44: =B71-B72 -> 562 | C44: =C71-C72 -> 0 | D44: =D71-D72 -> 35 | E44: CHECK / AGENT | F44: 2025: 1,270 − 708; 2024: none; 2023: 196 − 161. AR 2024 Note 8 p.204 detailed disposal-group net assets show €34m vs €35m from face totals due standalone rounding; face totals are used for the managerial identity. | G44: Non-operating net disposal-group asset; cash inside disposal group remains there.
A45: Non-current financial assets, excluding derivatives | B45: 45 | C45: 81 | D45: 46 | E45: CHECK / AGENT | F45: AR 2025 Note 24 p.230: 77−32 / 90−9; AR 2024 Note 24 p.217: 53−7 | G45: Non-operating financial assets; excludes operating derivatives. Note 24 is a mixed financial-asset caption; classification follows the team workbook convention.
A46: Non-operating assets | B46: =SUM(B43:B45) -> 820 | C46: =SUM(C43:C45) -> 427 | D46: =SUM(D43:D45) -> 454 | E46: CHECK / AGENT | F46: Sum of equity-method investments + net held-for-sale assets + non-current financial assets | G46: Non-operating asset pool.
A47: Total gross invested capital | B47: =B39+B46 -> 13720 | C47: =C39+C46 -> 12460 | D47: =D39+D46 -> 10261 | E47: AGENT | F47: Gross operating invested capital + non-operating assets | G47: Managerial gross invested capital.
A48: Total net invested capital | B48: =B40+B46 -> 5612 | C48: =C40+C46 -> 5933 | D48: =D40+D46 -> 4947 | E48: CHECK / AGENT | F48: Net operating invested capital + non-operating assets | G48: Must reconcile to equity + NFP + net tax position + separately classified other liabilities.
A50: FINANCING, TAX AND EQUITY
A51: Reported financial debts (including lease liabilities) | B51: 1281 | C51: 2423 | D51: 1913 | E51: 2025/24 CHECK; 2023 AGENT | F51: AR 2025 Note 29 p.241; AR 2024 Note 29 p.227 | G51: Financial debt; includes lease liabilities.
A52: Other financing liabilities, excluding operating derivatives | B52: 23 | C52: 77 | D52: 97 | E52: CHECK / AGENT | F52: AR 2025 Note 30 p.243; AR 2024 Note 30 p.230 | G52: Other financial liabilities are treated as financing; immaterial acquisition-related amounts, if any, remain here.
A53: Less: cash and cash equivalents | B53: -1650 | C53: -1184 | D53: -850 | E53: 2025/24 CHECK; 2023 AGENT | F53: AR 2025 p.200; AR 2024 p.189 | G53: All cash is financial; no working-cash carve-out.
A54: Less: current financial assets, excluding derivatives | B54: -41 | C54: -81 | D54: -77 | E54: CHECK / AGENT | F54: AR 2025 Note 24 p.230: 89−48 / 113−32; AR 2024 Note 24 p.217: 95−18 | G54: Netted in NFP; operating derivatives are excluded. Note 24 is a mixed financial-asset caption; classification follows the team workbook convention.
A55: Net financial position (NFP) | B55: =SUM(B51:B54) -> -387 | C55: =SUM(C51:C54) -> 1235 | D55: =SUM(D51:D54) -> 1083 | E55: CHECK / AGENT | F55: Financial debt + other financing liabilities − cash − current financial assets | G55: Positive = net financial obligations; negative = net financial assets/liquidity.
A56: Deferred tax liabilities | B56: 363 | C56: 356 | D56: 260 | E56: AGENT | F56: AR 2025 p.200; AR 2024 p.189 | G56: Tax position.
A57: Income tax liabilities | B57: 200 | C57: 118 | D57: 108 | E57: AGENT | F57: AR 2025 p.200; AR 2024 p.189 | G57: Tax position.
A58: Other-tax liabilities | B58: 184 | C58: 102 | D58: 113 | E58: AGENT | F58: AR 2025 Note 30 p.243; AR 2024 Note 30 p.230 | G58: Tax position.
A59: Total tax liabilities | B59: =SUM(B56:B58) -> 747 | C59: =SUM(C56:C58) -> 576 | D59: =SUM(D56:D58) -> 481 | E59: AGENT | F59: Deferred + income + other-tax liabilities | G59: Tax position.
A60: Less: deferred tax assets | B60: -165 | C60: -172 | D60: -164 | E60: AGENT | F60: AR 2025 p.200; AR 2024 p.189 | G60: Tax position.
A61: Less: income tax receivables | B61: -11 | C61: -57 | D61: -13 | E61: AGENT | F61: AR 2025 p.200; AR 2024 p.189 | G61: Tax position.
A62: Less: other-tax assets | B62: -186 | C62: -114 | D62: -83 | E62: AGENT | F62: AR 2025 Note 24 p.230; AR 2024 Note 24 p.217 | G62: Tax position.
A63: Net tax position | B63: =SUM(B59:B62) -> 385 | C63: =SUM(C59:C62) -> 233 | D63: =SUM(D59:D62) -> 221 | E63: CHECK / AGENT | F63: Tax liabilities − tax assets | G63: Shown separately from operating liabilities.
A64: Separately classified other liabilities | B64: 0 | C64: 0 | D64: 0 | E64: AGENT | F64: No material separately classified balance identified; held-for-sale positions are net assets in 2025/2023 | G64: No material divestment/investment payable requiring separate classification identified.
A65: Equity (including non-controlling interests) | B65: 5614 | C65: 4465 | D65: 3643 | E65: 2025/24 CHECK; 2023 AGENT | F65: AR 2025 p.200; AR 2024 p.189 | G65: Consolidated equity including NCI, per methodology.
A66: Total financing | B66: =B55+B63+B64+B65 -> 5612 | C66: =C55+C63+C64+C65 -> 5933 | D66: =D55+D63+D64+D65 -> 4947 | E66: CHECK / AGENT | F66: Equity + NFP + net tax position + separately classified other liabilities | G66: Financing side of managerial identity.
A67: Managerial identity residual | B67: =B48-B66 -> 0 | C67: =C48-C66 -> 0 | D67: =D48-D66 -> 0 | E67: AGENT | F67: Total net invested capital − total financing | G67: Should be zero; any non-zero amount requires explanation.
A69: MEMO / SCOPE CHECK
A70: Reported total assets | B70: 16772 | C70: 14344 | D70: 11707 | E70: 2025/24 CHECK; 2023 AGENT | F70: AR 2025 p.200; AR 2024 p.189 | G70: Reported total assets; not replaced by managerial invested-capital totals.
A71: Held-for-sale assets (reported) | B71: 1270 | C71: 0 | D71: 196 | E71: AGENT | F71: AR 2025 p.200 / Note 8 pp.215–216; AR 2024 p.189 / Note 8 p.204 | G71: Memo only.
A72: Held-for-sale liabilities (reported) | B72: 708 | C72: 0 | D72: 161 | E72: AGENT | F72: AR 2025 p.200 / Note 8 pp.215–216; AR 2024 p.189 / Note 8 p.204 | G72: Memo only.

Sheet ROE
A1: Rheinmetall AG — ROE Analysis
A2: € million | IFRS | Fiscal year ended 31 December | Consolidated incl. NCI | Closing equity
A3: 2025 and 2024 income-statement figures use the 2025 Annual Report (2024 restated for IFRS 5); 2023 is as reported in the 2024 Annual Report. The 2024 managerial balance sheet is not restated for the 2025 civilian-business discontinuation, so return decompositions using 2024 closing balance-sheet amounts retain that scope mismatch.
A5: ROE SUMMARY
A6: Measure / input | B6: 2025 | C6: 2024 Restated | D6: 2023 As reported | E6: Status | F6: Source / calculation | G6: Notes
A7: ROE on net income — direct | B7: ='Reformulated IS'!B80/'Managerial BS'!B65 -> 0.1487353 | C7: ='Reformulated IS'!C80/'Managerial BS'!C65 -> 0.18096305 | D7: ='Reformulated IS'!D80/'Managerial BS'!D65 -> 0.16085644 | E7: AGENT | F7: Reported net income / closing equity | G7: DuPont direct check.
A8: ROE on comprehensive income — direct | B8: ='Reformulated IS'!B34/'Managerial BS'!B65 -> 0.14000713 | C8: ='Reformulated IS'!C34/'Managerial BS'!C65 -> 0.2237402 | D8: ='Reformulated IS'!D34/'Managerial BS'!D65 -> 0.16387593 | E8: AGENT | F8: Reformulated IS total comprehensive income / closing equity | G8: Consolidated incl. NCI.
A9: OCI / equity bridge | B9: =('Reformulated IS'!B34-'Reformulated IS'!B80)/'Managerial BS'!B65 -> -0.0087281796 | C9: =('Reformulated IS'!C34-'Reformulated IS'!C80)/'Managerial BS'!C65 -> 0.042777156 | D9: =('Reformulated IS'!D34-'Reformulated IS'!D80)/'Managerial BS'!D65 -> 0.0030194894 | E9: AGENT | F9: (Comprehensive income − net income) / closing equity | G9: Dirty-surplus bridge.
A10: Bridge check | B10: =B8-B7-B9 -> 0 | C10: =C8-C7-C9 -> 0 | D10: =D8-D7-D9 -> -7.3725748e-18 | E10: AGENT | F10: ROE(CI) − ROE(NI) − OCI/equity | G10: Should be zero.
A12: DUPONT — REPORTED FIGURES
A13: Measure / input | B13: 2025 | C13: 2024 Restated | D13: 2023 As reported | E13: Status | F13: Source / calculation | G13: Notes
A14: Net income | B14: ='Reformulated IS'!B80 -> 835 | C14: ='Reformulated IS'!C80 -> 808 | D14: ='Reformulated IS'!D80 -> 586 | E14: CHECK | F14: Reformulated IS reported-source input | G14: Reported figure.
A15: Continuing net income | B15: =B125 -> 1176 | C15: =C125 -> 840 | D15: =D125 -> 630 | E15: AGENT | F15: ROE support input; AR 2025 p.199; AR 2024 p.188 | G15: Reported continuing operations.
A16: Earnings before taxes (EBT) | B16: ='Reformulated IS'!B79 -> 1572 | C16: ='Reformulated IS'!C79 -> 1168 | D16: ='Reformulated IS'!D79 -> 815 | E16: CHECK | F16: Reformulated IS reported-source input | G16: Reported continuing EBT.
A17: EBIT | B17: =B124 -> 1684 | C17: =C124 -> 1270 | D17: =D124 -> 897 | E17: AGENT | F17: ROE support input; AR 2025 p.199; AR 2024 p.188 | G17: Reported EBIT.
A18: Sales | B18: ='Reformulated IS'!B7 -> 9935 | C18: ='Reformulated IS'!C7 -> 7715 | D18: ='Reformulated IS'!D7 -> 7176 | E18: CHECK | F18: Reformulated IS | G18: Reported sales.
A19: Total assets | B19: ='Managerial BS'!B70 -> 16772 | C19: ='Managerial BS'!C70 -> 14344 | D19: ='Managerial BS'!D70 -> 11707 | E19: CHECK | F19: Managerial BS — reported total assets | G19: Closing balance.
A20: Equity incl. NCI | B20: ='Managerial BS'!B65 -> 5614 | C20: ='Managerial BS'!C65 -> 4465 | D20: ='Managerial BS'!D65 -> 3643 | E20: CHECK | F20: Managerial BS — equity incl. NCI | G20: Closing balance.
A21: Tax effect = continuing net income / EBT | B21: =B15/B16 -> 0.7480916 | C21: =C15/C16 -> 0.71917808 | D21: =D15/D16 -> 0.77300613 | E21: AGENT | F21: Continuing net income / EBT | G21: Tax effect in DuPont split.
A22: Discontinued effect = net income / continuing net income | B22: =B14/B15 -> 0.71003401 | C22: =C14/C15 -> 0.96190476 | D22: =D14/D15 -> 0.93015873 | E22: AGENT | F22: Net income / continuing net income | G22: Discontinued-operations effect.
A23: Net income / EBT | B23: =B14/B16 -> 0.53117048 | C23: =C14/C16 -> 0.69178082 | D23: =D14/D16 -> 0.7190184 | E23: AGENT | F23: Net income / EBT | G23: Should equal tax effect × discontinued effect.
A24: Tax × discontinued split check | B24: =B21*B22-B23 -> 0 | C24: =C21*C22-C23 -> 0 | D24: =D21*D22-D23 -> 0 | E24: AGENT | F24: Tax effect × discontinued effect − net income/EBT | G24: Should be zero.
A25: EBT / EBIT | B25: =B16/B17 -> 0.93349169 | C25: =C16/C17 -> 0.91968504 | D25: =D16/D17 -> 0.90858417 | E25: AGENT | F25: EBT / EBIT | G25: Reported DuPont.
A26: EBIT / sales | B26: =B17/B18 -> 0.16950176 | C26: =C17/C18 -> 0.16461439 | D26: =D17/D18 -> 0.125 | E26: AGENT | F26: EBIT / sales | G26: Reported DuPont.
A27: Sales / total assets | B27: =B18/B19 -> 0.59235631 | C27: =C18/C19 -> 0.53785555 | D27: =D18/D19 -> 0.6129666 | E27: AGENT | F27: Sales / total assets | G27: Closing-balance turnover.
A28: Total assets / equity | B28: =B19/B20 -> 2.9875312 | C28: =C19/C20 -> 3.212542 | D28: =D19/D20 -> 3.2135603 | E28: AGENT | F28: Total assets / equity | G28: Closing-balance leverage.
A29: DuPont ROE | B29: =B23*B25*B26*B27*B28 -> 0.1487353 | C29: =C23*C25*C26*C27*C28 -> 0.18096305 | D29: =D23*D25*D26*D27*D28 -> 0.16085644 | E29: AGENT | F29: Product of DuPont factors | G29: Reported DuPont ROE.
A30: Direct ROE on net income | B30: =B14/B20 -> 0.1487353 | C30: =C14/C20 -> 0.18096305 | D30: =D14/D20 -> 0.16085644 | E30: AGENT | F30: Net income / equity | G30: Direct check.
A31: Decomposition check | B31: =B29-B30 -> 0 | C31: =C29-C30 -> 0 | D31: =D29-D30 -> 0 | E31: AGENT | F31: DuPont ROE − direct ROE | G31: Technical tolerance 0.01 pp.
A33: DUPONT LIMITATIONS — QUANTIFIED
A34: Measure / input | B34: 2025 | C34: 2024 Restated | D34: 2023 As reported | E34: Status | F34: Source / calculation | G34: Notes
A35: 1. Core return on sales | B35: ='Reformulated IS'!B18/'Reformulated IS'!B7 -> 0.15249119 | C35: ='Reformulated IS'!C18/'Reformulated IS'!C7 -> 0.16357745 | D35: ='Reformulated IS'!D18/'Reformulated IS'!D7 -> 0.11162207 | E35: AGENT | F35: Reformulated IS core operating income / sales | G35: Limitation 1.
A36: 1. Reported EBIT / sales | B36: =B17/B18 -> 0.16950176 | C36: =C17/C18 -> 0.16461439 | D36: =D17/D18 -> 0.125 | E36: AGENT | F36: Reported EBIT / sales | G36: Limitation 1.
A37: 1. Margin-definition difference | B37: =B35-B36 -> -0.017010569 | C37: =C35-C36 -> -0.001036941 | D37: =D35-D36 -> -0.013377926 | E37: AGENT | F37: Core ROS − reported EBIT margin | G37: Quantifies margin-definition difference.
A38: 2. Operating turnover = sales / gross operating invested capital | B38: ='Reformulated IS'!B7/'Managerial BS'!B39 -> 0.77015504 | C38: ='Reformulated IS'!C7/'Managerial BS'!C39 -> 0.64115349 | D38: ='Reformulated IS'!D7/'Managerial BS'!D39 -> 0.73172224 | E38: AGENT | F38: Sales / managerial gross operating invested capital | G38: Limitation 2.
A39: 2. Total-asset turnover | B39: ='Reformulated IS'!B7/'Managerial BS'!B70 -> 0.59235631 | C39: ='Reformulated IS'!C7/'Managerial BS'!C70 -> 0.53785555 | D39: ='Reformulated IS'!D7/'Managerial BS'!D70 -> 0.6129666 | E39: AGENT | F39: Sales / reported total assets | G39: Limitation 2.
A40: 2. Turnover-definition difference | B40: =B38-B39 -> 0.17779873 | C40: =C38-C39 -> 0.10329795 | D40: =D38-D39 -> 0.11875564 | E40: AGENT | F40: Operating turnover − total-asset turnover | G40: Quantifies denominator effect.
A41: 3. Operating liabilities / equity | B41: ='Managerial BS'!B29/'Managerial BS'!B65 -> 1.4442465 | C41: ='Managerial BS'!C29/'Managerial BS'!C65 -> 1.4618141 | D41: ='Managerial BS'!D29/'Managerial BS'!D65 -> 1.4586879 | E41: AGENT | F41: Managerial operating liabilities / equity | G41: Limitation 3.
A42: 3. Financial debt + other financing liabilities / equity | B42: =('Managerial BS'!B51+'Managerial BS'!B52)/'Managerial BS'!B65 -> 0.23227645 | C42: =('Managerial BS'!C51+'Managerial BS'!C52)/'Managerial BS'!C65 -> 0.55991041 | D42: =('Managerial BS'!D51+'Managerial BS'!D52)/'Managerial BS'!D65 -> 0.55174307 | E42: AGENT | F42: Managerial financial debt + other financing liabilities / equity | G42: Limitation 3.
A43: 3. Total assets / equity | B43: ='Managerial BS'!B70/'Managerial BS'!B65 -> 2.9875312 | C43: ='Managerial BS'!C70/'Managerial BS'!C65 -> 3.212542 | D43: ='Managerial BS'!D70/'Managerial BS'!D65 -> 3.2135603 | E43: AGENT | F43: Reported total assets / equity | G43: Reported leverage context.
A44: 4. Interest income | B44: ='Reformulated IS'!B23 -> 4 | C44: ='Reformulated IS'!C23 -> 14 | D44: ='Reformulated IS'!D23 -> 29 | E44: CHECK | F44: Reformulated IS interest income | G44: Limitation 4.
A45: 4. Interest income / EBIT | B45: =B44/B17 -> 0.0023752969 | C45: =C44/C17 -> 0.011023622 | D45: =D44/D17 -> 0.032329989 | E45: AGENT | F45: Interest income / reported EBIT | G45: Quantifies financial-income location.
A46: 5. |Unusual items| / |income before unusual items and taxes| | B46: =ABS('Reformulated IS'!B27)/ABS('Reformulated IS'!B26) -> 0.098408104 | C46: =ABS('Reformulated IS'!C27)/ABS('Reformulated IS'!C26) -> 0.24239714 | D46: =ABS('Reformulated IS'!D27)/ABS('Reformulated IS'!D26) -> 0.071129707 | E46: AGENT | F46: |Unusual items| / |income before unusual items and taxes| | G46: Limitation 5.
A48: MODIGLIANI–MILLER — SELECTED: SECOND ADJUSTMENT (NET FINANCIAL OBLIGATIONS / ASSETS)
A49: Selected formulation: second adjustment. Operating liabilities exist and financial assets are classified outside operations. Use the NFO branch when NFO > 0 and the NFA branch when financial assets exceed financial obligations.
A50: Measure / input | B50: 2025 | C50: 2024 Restated | D50: 2023 As reported | E50: Status | F50: Source / calculation | G50: Notes
A51: Net operating invested capital | B51: ='Managerial BS'!B40 -> 4792 | C51: ='Managerial BS'!C40 -> 5506 | D51: ='Managerial BS'!D40 -> 4493 | E51: CHECK | F51: Managerial BS | G51: Closing balance.
A52: Net tax position | B52: ='Managerial BS'!B63 -> 385 | C52: ='Managerial BS'!C63 -> 233 | D52: ='Managerial BS'!D63 -> 221 | E52: CHECK | F52: Managerial BS | G52: Closing balance.
A53: Net operating assets | B53: =B51-B52 -> 4407 | C53: =C51-C52 -> 5273 | D53: =D51-D52 -> 4272 | E53: AGENT | F53: Net operating invested capital − net tax position | G53: Net operating assets.
A54: Net financial position (NFP) | B54: ='Managerial BS'!B55 -> -387 | C54: ='Managerial BS'!C55 -> 1235 | D54: ='Managerial BS'!D55 -> 1083 | E54: CHECK | F54: Managerial BS | G54: Positive = NFO component; negative = net liquidity.
A55: Separately classified other liabilities | B55: ='Managerial BS'!B64 -> 0 | C55: ='Managerial BS'!C64 -> 0 | D55: ='Managerial BS'!D64 -> 0 | E55: CHECK | F55: Managerial BS | G55: No material separate liabilities identified.
A56: Non-operating assets | B56: ='Managerial BS'!B46 -> 820 | C56: ='Managerial BS'!C46 -> 427 | D56: ='Managerial BS'!D46 -> 454 | E56: CHECK | F56: Managerial BS | G56: Non-operating asset pool.
A57: Net financial obligations (NFO) | B57: =B54+B55-B56 -> -1207 | C57: =C54+C55-C56 -> 808 | D57: =D54+D55-D56 -> 629 | E57: AGENT | F57: NFP + separately classified other liabilities − non-operating assets | G57: NFO can be negative.
A58: Net financial assets (NFA) | B58: =IF(B57<0,-B57,0) -> 1207 | C58: =IF(C57<0,-C57,0) -> 0 | D58: =IF(D57<0,-D57,0) -> 0 | E58: AGENT | F58: If NFO < 0, NFA = −NFO | G58: Only NFA branch when positive.
A59: Branch used | B59: =IF(B57>0,"NFO","NFA") -> NFA | C59: =IF(C57>0,"NFO","NFA") -> NFO | D59: =IF(D57>0,"NFO","NFA") -> NFO | E59: AGENT | F59: Branch selected from sign of NFO | G59: 2025 NFA; 2024/2023 NFO.
A60: Equity incl. NCI | B60: ='Managerial BS'!B65 -> 5614 | C60: ='Managerial BS'!C65 -> 4465 | D60: ='Managerial BS'!D65 -> 3643 | E60: CHECK | F60: Managerial BS | G60: Consolidated incl. NCI.
A61: Identity check: net operating assets − NFO − equity | B61: =B53-B57-B60 -> 0 | C61: =C53-C57-C60 -> 0 | D61: =D53-D57-D60 -> 0 | E61: AGENT | F61: Net operating assets − NFO − equity | G61: Required identity; should be zero.
A62: Core operating income | B62: ='Reformulated IS'!B18 -> 1515 | C62: ='Reformulated IS'!C18 -> 1262 | D62: ='Reformulated IS'!D18 -> 801 | E62: CHECK | F62: Reformulated IS | G62: Stage-3 operating numerator.
A63: Stage-3 financial result = non-core operating income + net financial result | B63: ='Reformulated IS'!B21+'Reformulated IS'!B25 -> -133 | C63: ='Reformulated IS'!C21+'Reformulated IS'!C25 -> -144 | D63: ='Reformulated IS'!D21+'Reformulated IS'!D25 -> -84 | E63: AGENT | F63: Non-core operating income + net financial result | G63: Stage-3 financial result.
A64: Return on net operating assets | B64: =B62/B53 -> 0.34377127 | C64: =C62/C53 -> 0.23933245 | D64: =D62/D53 -> 0.1875 | E64: AGENT | F64: Core operating income / net operating assets | G64: RNOA, pre-tax M-M basis.
A65: Cost of NFO | B65: =IF(B57>0,-B63/B57,"") | C65: =IF(C57>0,-C63/C57,"") -> 0.17821782 | D65: =IF(D57>0,-D63/D57,"") -> 0.13354531 | E65: AGENT | F65: − stage-3 financial result / NFO | G65: Calculated only when NFO > 0.
A66: Return on NFA | B66: =IF(B57<0,B63/B58,"") -> -0.11019056 | C66: =IF(C57<0,C63/C58,"") | D66: =IF(D57<0,D63/D58,"") | E66: AGENT | F66: Stage-3 financial result / NFA | G66: Calculated only when NFA > 0.
A67: NFO / equity | B67: =IF(B57>0,B57/B60,0) -> 0 | C67: =IF(C57>0,C57/C60,0) -> 0.18096305 | D67: =IF(D57>0,D57/D60,0) -> 0.1726599 | E67: AGENT | F67: NFO / equity | G67: NFO branch leverage.
A68: NFA / equity | B68: =IF(B58>0,B58/B60,0) -> 0.21499822 | C68: =IF(C58>0,C58/C60,0) -> 0 | D68: =IF(D58>0,D58/D60,0) -> 0 | E68: AGENT | F68: NFA / equity | G68: NFA branch weight.
A69: Pre-multiplier bracket | B69: =IF(B57>0,B64+(B64-B65)*B57/B60,B64-(B64-B66)*B58/B60) -> 0.24617029 | C69: =IF(C57>0,C64+(C64-C65)*C57/C60,C64-(C64-C66)*C58/C60) -> 0.25039194 | D69: =IF(D57>0,D64+(D64-D65)*D57/D60,D64-(D64-D66)*D58/D60) -> 0.19681581 | E69: AGENT | F69: Selected second-adjustment branch | G69: Pre-multiplier bracket.
A70: Income before unusual items and taxes | B70: ='Reformulated IS'!B26 -> 1382 | C70: ='Reformulated IS'!C26 -> 1118 | D70: ='Reformulated IS'!D26 -> 717 | E70: CHECK | F70: Reformulated IS | G70: Recurring pre-unusual pre-tax income.
A71: Total comprehensive income | B71: ='Reformulated IS'!B34 -> 786 | C71: ='Reformulated IS'!C34 -> 999 | D71: ='Reformulated IS'!D34 -> 597 | E71: CHECK | F71: Reformulated IS | G71: Reported comprehensive income bridge.
A72: Final multiplier | B72: =B71/B70 -> 0.56874096 | C72: =C71/C70 -> 0.89355993 | D72: =D71/D70 -> 0.83263598 | E72: AGENT | F72: Comprehensive income / income before unusual items and taxes | G72: Final multiplier.
A73: Modigliani–Miller ROE | B73: =B69*B72 -> 0.14000713 | C73: =C69*C72 -> 0.2237402 | D73: =D69*D72 -> 0.16387593 | E73: AGENT | F73: Selected M-M bracket × final multiplier | G73: Principal M-M decomposition.
A74: Direct ROE on comprehensive income | B74: =B71/B60 -> 0.14000713 | C74: =C71/C60 -> 0.2237402 | D74: =D71/D60 -> 0.16387593 | E74: AGENT | F74: Comprehensive income / equity | G74: Direct check.
A75: Decomposition check | B75: =B73-B74 -> 0 | C75: =C73-C74 -> 0 | D75: =D73-D74 -> 0 | E75: AGENT | F75: M-M ROE − direct ROE | G75: Technical tolerance 0.01 pp.
A77: PENMAN
A78: Uniform tax rate is the simplifying allocation required by the methodology. The ROOA split stops unless a short-term borrowing rate is available from short-term interest expense / short-term financial liabilities or from a team-supplied market rate.
A79: Measure / input | B79: 2025 | C79: 2024 Restated | D79: 2023 As reported | E79: Status | F79: Source / calculation | G79: Notes
A80: Recurring continuing tax expense — positive magnitude | B80: =-'Reformulated IS'!B29 -> 395 | C80: =-'Reformulated IS'!C29 -> 327 | D80: =-'Reformulated IS'!D29 -> 188 | E80: CHECK | F80: − Reformulated IS recurring continuing tax expense | G80: Positive magnitude.
A81: Reported continuing EBT | B81: ='Reformulated IS'!B79 -> 1572 | C81: ='Reformulated IS'!C79 -> 1168 | D81: ='Reformulated IS'!D79 -> 815 | E81: CHECK | F81: Reformulated IS reported EBT | G81: Denominator for uniform tax rate.
A82: Uniform tax rate | B82: =B80/B81 -> 0.25127226 | C82: =C80/C81 -> 0.27996575 | D82: =D80/D81 -> 0.23067485 | E82: AGENT | F82: Recurring continuing tax expense / reported continuing EBT | G82: Simplifying uniform allocation.
A83: Statutory tax rate | B83: =B126 -> 0.3 | C83: =C126 -> 0.3 | D83: =D126 -> 0.3 | E83: AGENT | F83: ROE support input; tax note | G83: 30% statutory rate.
A84: Uniform − statutory tax rate | B84: =B82-B83 -> -0.048727735 | C84: =C82-C83 -> -0.020034247 | D84: =D82-D83 -> -0.069325153 | E84: AGENT | F84: Uniform tax rate − statutory rate | G84: Tax-rate comparison.
A85: Core operating income | B85: ='Reformulated IS'!B18 -> 1515 | C85: ='Reformulated IS'!C18 -> 1262 | D85: ='Reformulated IS'!D18 -> 801 | E85: CHECK | F85: Reformulated IS | G85: Recurring core operating numerator.
A86: NOPAT | B86: =B85*(1-B82) -> 1134.3225 | C86: =C85*(1-C82) -> 908.68322 | D86: =D85*(1-D82) -> 616.22945 | E86: AGENT | F86: Core operating income × (1 − uniform tax rate) | G86: NOPAT.
A87: Stage-3 financial result | B87: =B63 -> -133 | C87: =C63 -> -144 | D87: =D63 -> -84 | E87: AGENT | F87: M-M stage-3 financial result | G87: Financial result aligned to non-operating assets.
A88: Net financial expenses — positive magnitude | B88: =-B87 -> 133 | C88: =-C87 -> 144 | D88: =-D87 -> 84 | E88: AGENT | F88: − stage-3 financial result | G88: Positive expense magnitude when stage-3 result is negative.
A89: Net financial expenses, net of tax | B89: =B88*(1-B82) -> 99.580789 | C89: =C88*(1-C82) -> 103.68493 | D89: =D88*(1-D82) -> 64.623313 | E89: AGENT | F89: Net financial expenses × (1 − uniform tax rate) | G89: After-tax financial expense.
A90: Income before unusual items and taxes | B90: ='Reformulated IS'!B26 -> 1382 | C90: ='Reformulated IS'!C26 -> 1118 | D90: ='Reformulated IS'!D26 -> 717 | E90: CHECK | F90: Reformulated IS | G90: Recurring pre-unusual pre-tax income.
A91: Income before unusual items after tax | B91: =B90*(1-B82) -> 1034.7417 | C91: =C90*(1-C82) -> 804.99829 | D91: =D90*(1-D82) -> 551.60613 | E91: AGENT | F91: Income before unusual items and taxes × (1 − uniform tax rate) | G91: Penman denominator for final multiplier.
A92: Net operating assets | B92: =B53 -> 4407 | C92: =C53 -> 5273 | D92: =D53 -> 4272 | E92: AGENT | F92: M-M net operating assets | G92: Same managerial classification.
A93: RNOA = NOPAT / net operating assets | B93: =B86/B92 -> 0.25739109 | C93: =C86/C92 -> 0.17232756 | D93: =D86/D92 -> 0.14424847 | E93: AGENT | F93: NOPAT / net operating assets | G93: Penman RNOA.
A94: Operating liabilities incl. tax | B94: ='Managerial BS'!B29+'Managerial BS'!B63 -> 8493 | C94: ='Managerial BS'!C29+'Managerial BS'!C63 -> 6760 | D94: ='Managerial BS'!D29+'Managerial BS'!D63 -> 5535 | E94: AGENT | F94: Operating liabilities + net tax position | G94: All net tax positions are liabilities in the analysed years.
A95: Short-term borrowing rate | B95: =IF(B129="","",B129) | C95: =IF(C129="","",C129) | D95: =IF(D129="","",D129) | E95: INPUT REQUIRED | F95: ROE support input row 129 | G95: No short-term rate is inferred.
A96: Short-term borrowing rate, after tax | B96: =IF(B95="","",B95*(1-B82)) | C96: =IF(C95="","",C95*(1-C82)) | D96: =IF(D95="","",D95*(1-D82)) | E96: AGENT | F96: Short-term borrowing rate × (1 − uniform tax rate) | G96: Blank until rate supplied.
A97: Implicit interest | B97: =IF(B95="","",B94*B95*(1-B82)) | C97: =IF(C95="","",C94*C95*(1-C82)) | D97: =IF(D95="","",D94*D95*(1-D82)) | E97: AGENT | F97: Operating liabilities incl. tax × short-term rate × (1 − uniform rate) | G97: Blank until rate supplied.
A98: ROOA | B98: =IF(B95="","",(B86+B97)/'Managerial BS'!B39) | C98: =IF(C95="","",(C86+C97)/'Managerial BS'!C39) | D98: =IF(D95="","",(D86+D97)/'Managerial BS'!D39) | E98: AGENT | F98: (NOPAT + implicit interest) / gross operating invested capital | G98: Blank until rate supplied.
A99: RNOA from ROOA split | B99: =IF(B95="","",B98+(B98-B96)*B94/B92) | C99: =IF(C95="","",C98+(C98-C96)*C94/C92) | D99: =IF(D95="","",D98+(D98-D96)*D94/D92) | E99: AGENT | F99: ROOA + spread × operating-liability leverage | G99: Blank until rate supplied.
A100: ROOA split check | B100: =IF(B95="","",B99-B93) | C100: =IF(C95="","",C99-C93) | D100: =IF(D95="","",D99-D93) | E100: AGENT | F100: RNOA from ROOA split − direct RNOA | G100: Blank until rate supplied.
A101: After-tax operating contribution = NOPAT / equity | B101: =B86/B60 -> 0.20205246 | C101: =C86/C60 -> 0.20351248 | D101: =D86/D60 -> 0.16915439 | E101: AGENT | F101: NOPAT / equity | G101: After-tax operating contribution.
A102: After-tax financing contribution = −NFE after tax / equity | B102: =-B89/B60 -> -0.017737939 | C102: =-C89/C60 -> -0.023221709 | D102: =-D89/D60 -> -0.017739037 | E102: AGENT | F102: − NFE after tax / equity | G102: After-tax financing contribution.
A103: Penman bracket after tax | B103: =B101+B102 -> 0.18431452 | C103: =C101+C102 -> 0.18029077 | D103: =D101+D102 -> 0.15141535 | E103: AGENT | F103: Operating + financing contribution | G103: Equals income before unusual items after tax / equity.
A104: Final multiplier | B104: =B71/B91 -> 0.75960984 | C104: =C71/C91 -> 1.2409964 | D104: =D71/D91 -> 1.082294 | E104: AGENT | F104: Comprehensive income / income before unusual items after tax | G104: Final multiplier; comprehensive income is not taxed again.
A105: Penman ROE — direct bracket | B105: =B103*B104 -> 0.14000713 | C105: =C103*C104 -> 0.2237402 | D105: =D103*D104 -> 0.16387593 | E105: AGENT | F105: Penman after-tax bracket × final multiplier | G105: Direct Penman ROE; ROOA sub-split remains unavailable.
...

Sheet ROI
A1: Rheinmetall AG — ROI Analysis
A2: € million | IFRS | Fiscal year ended 31 December | Consolidated incl. NCI | Closing invested-capital balances
A3: ROI is calculated only from the current Reformulated IS and Managerial BS sheets, as required. 2025/2024 income-statement figures use the 2025 Annual Report (2024 restated for IFRS 5); 2023 is as reported in the 2024 Annual Report. The 2024 managerial balance sheet is not restated for the 2025 civilian-business discontinuation, so 2024 return measures retain that scope mismatch.
A5: ROI COMPARISON TO TEAM WORKBOOK
A6: Measure | B6: Year | C6: Workbook | D6: Agent | E6: Difference (pp) | F6: Status | G6: Source / calculation
A7: Gross ROI | B7: 2025 | C7: 0.10911079 | D7: =B28 -> 0.10889213 | E7: =IF(C7="","",(D7-C7)*100) -> -0.021865889 | F7: =IF(C7="","AGENT",IF(ABS(D7-C7)<=0.0001,"MATCH","WORKBOOK DEFECT")) -> WORKBOOK DEFECT | G7: Team workbook ROI + Decomposition vs current step-by-step workbook. 2025 difference traces to the current Reformulated IS omitting the disclosed €3m NVL acquisition transaction cost add-back; source IS is not changed in this ROI step.
A8: Gross ROI | B8: 2024 | C8: 0.097431782 | D8: =C28 -> 0.097913323 | E8: =IF(C8="","",(D8-C8)*100) -> 0.048154093 | F8: =IF(C8="","AGENT",IF(ABS(D8-C8)<=0.0001,"MATCH","WORKBOOK DEFECT")) -> WORKBOOK DEFECT | G8: Team workbook ROI + Decomposition vs current step-by-step workbook. 2024 team ROI uses operating income €6m below the current Reformulated IS, consistent with not removing the €6m Loc Performance acquisition transaction cost.
A9: Gross ROI | B9: 2023 | D9: =D28 -> 0.077867654 | E9: =IF(C9="","",(D9-C9)*100) | F9: =IF(C9="","AGENT",IF(ABS(D9-C9)<=0.0001,"MATCH","METHOD DIFFERENCE")) -> AGENT | G9: No 2023 ROI result is present in the supplied team workbook; Agent result only.
A10: Net ROI | B10: 2025 | C10: 0.26674982 | D10: =B48 -> 0.26621525 | E10: =IF(C10="","",(D10-C10)*100) -> -0.053456878 | F10: =IF(C10="","AGENT",IF(ABS(D10-C10)<=0.0001,"MATCH","WORKBOOK DEFECT")) -> WORKBOOK DEFECT | G10: Same 2025 operating-income difference as Gross ROI; denominators are from the current Managerial BS.
A11: Net ROI | B11: 2024 | C11: 0.20461824 | D11: =C48 -> 0.20562953 | E11: =IF(C11="","",(D11-C11)*100) -> 0.10112928 | F11: =IF(C11="","AGENT",IF(ABS(D11-C11)<=0.0001,"MATCH","WORKBOOK DEFECT")) -> WORKBOOK DEFECT | G11: Same 2024 operating-income difference as Gross ROI; denominators are from the current Managerial BS.
A12: Net ROI | B12: 2023 | D12: =D48 -> 0.16151203 | E12: =IF(C12="","",(D12-C12)*100) | F12: =IF(C12="","AGENT",IF(ABS(D12-C12)<=0.0001,"MATCH","METHOD DIFFERENCE")) -> AGENT | G12: No 2023 ROI result is present in the supplied team workbook; Agent result only.
A14: GROSS ROI DECOMPOSITION
A15: Measure / input | B15: 2025 | C15: 2024 Restated | D15: 2023 As reported | E15: Status | F15: Source / calculation | G15: Notes
A16: Core operating income | B16: ='Reformulated IS'!B18 -> 1515 | C16: ='Reformulated IS'!C18 -> 1262 | D16: ='Reformulated IS'!D18 -> 801 | E16: CHECK | F16: Reformulated IS — Core Operating Income | G16: Recurring core operating numerator.
A17: Gross operating invested capital | B17: ='Managerial BS'!B39 -> 12900 | C17: ='Managerial BS'!C39 -> 12033 | D17: ='Managerial BS'!D39 -> 9807 | E17: CHECK | F17: Managerial BS — Gross operating invested capital | G17: Closing balance; gross means before operating liabilities.
A18: Core return on gross operating invested capital | B18: =B16/B17 -> 0.11744186 | C18: =C16/C17 -> 0.10487825 | D18: =D16/D17 -> 0.081676354 | E18: AGENT | F18: Core operating income / gross operating invested capital | G18: Core gross return.
A19: Core capital weight | B19: =B17/B27 -> 0.94023324 | C19: =C17/C27 -> 0.96573034 | D19: =D17/D27 -> 0.9557548 | E19: AGENT | F19: Gross operating invested capital / total gross invested capital | G19: Core share of total gross invested capital.
A20: Core contribution to Gross ROI | B20: =B18*B19 -> 0.11042274 | C20: =C18*C19 -> 0.10128411 | D20: =D18*D19 -> 0.078062567 | E20: AGENT | F20: Core return × core capital weight | G20: Weighted core contribution.
A21: Non-core operating income | B21: ='Reformulated IS'!B21 -> -21 | C21: ='Reformulated IS'!C21 -> -42 | D21: ='Reformulated IS'!D21 -> -2 | E21: CHECK | F21: Reformulated IS — Non-core Operating Income | G21: Recurring non-core operating numerator.
A22: Non-operating assets | B22: ='Managerial BS'!B46 -> 820 | C22: ='Managerial BS'!C46 -> 427 | D22: ='Managerial BS'!D46 -> 454 | E22: CHECK | F22: Managerial BS — Non-operating assets | G22: Closing non-operating asset pool.
A23: Non-core return on non-operating assets | B23: =IF(B22=0,"",B21/B22) -> -0.025609756 | C23: =IF(C22=0,"",C21/C22) -> -0.098360656 | D23: =IF(D22=0,"",D21/D22) -> -0.0044052863 | E23: AGENT | F23: Non-core operating income / non-operating assets | G23: Return on non-operating assets.
A24: Non-core capital weight | B24: =B22/B27 -> 0.059766764 | C24: =C22/C27 -> 0.034269663 | D24: =D22/D27 -> 0.0442452 | E24: AGENT | F24: Non-operating assets / total gross invested capital | G24: Non-core share of total gross invested capital.
A25: Non-core contribution to Gross ROI | B25: =B23*B24 -> -0.0015306122 | C25: =C23*C24 -> -0.0033707865 | D25: =D23*D24 -> -0.00019491278 | E25: AGENT | F25: Non-core return × non-core capital weight | G25: Weighted non-core contribution.
A26: Operating income | B26: ='Reformulated IS'!B22 -> 1494 | C26: ='Reformulated IS'!C22 -> 1220 | D26: ='Reformulated IS'!D22 -> 799 | E26: CHECK | F26: Reformulated IS — Operating Income | G26: Core + non-core operating income.
A27: Total gross invested capital | B27: ='Managerial BS'!B47 -> 13720 | C27: ='Managerial BS'!C47 -> 12460 | D27: ='Managerial BS'!D47 -> 10261 | E27: CHECK | F27: Managerial BS — Total gross invested capital | G27: Gross operating invested capital + non-operating assets.
A28: Gross ROI — direct | B28: =B26/B27 -> 0.10889213 | C28: =C26/C27 -> 0.097913323 | D28: =D26/D27 -> 0.077867654 | E28: AGENT | F28: Operating income / total gross invested capital | G28: Principal Gross ROI.
A29: Gross ROI — decomposed | B29: =B20+B25 -> 0.10889213 | C29: =C20+C25 -> 0.097913323 | D29: =D20+D25 -> 0.077867654 | E29: AGENT | F29: Core contribution + non-core contribution | G29: Required weighted decomposition.
A30: Decomposition check | B30: =B29-B28 -> 0 | C30: =C29-C28 -> 0 | D30: =D29-D28 -> 0 | E30: AGENT | F30: Decomposed Gross ROI − direct Gross ROI | G30: Technical tolerance: 0.01 pp.
A31: Capital weights total | B31: =B19+B24 -> 1 | C31: =C19+C24 -> 1 | D31: =D19+D24 -> 1 | E31: AGENT | F31: Core capital weight + non-core capital weight | G31: Must equal 100%.
A32: Capital weights check | B32: =B31-1 -> 0 | C32: =C31-1 -> 0 | D32: =D31-1 -> 0 | E32: AGENT | F32: Capital weights total − 100% | G32: Technical tolerance: 0.01 pp.
A34: NET ROI DECOMPOSITION
A35: Measure / input | B35: 2025 | C35: 2024 Restated | D35: 2023 As reported | E35: Status | F35: Source / calculation | G35: Notes
A36: Core operating income | B36: ='Reformulated IS'!B18 -> 1515 | C36: ='Reformulated IS'!C18 -> 1262 | D36: ='Reformulated IS'!D18 -> 801 | E36: CHECK | F36: Reformulated IS — Core Operating Income | G36: Recurring core operating numerator.
A37: Net operating invested capital | B37: ='Managerial BS'!B40 -> 4792 | C37: ='Managerial BS'!C40 -> 5506 | D37: ='Managerial BS'!D40 -> 4493 | E37: CHECK | F37: Managerial BS — Net operating invested capital | G37: Closing operating capital net of recurring operating liabilities.
A38: Core return on net operating invested capital | B38: =B36/B37 -> 0.31615192 | C38: =C36/C37 -> 0.2292045 | D38: =D36/D37 -> 0.17827732 | E38: AGENT | F38: Core operating income / net operating invested capital | G38: Core net return.
A39: Core capital weight | B39: =B37/B47 -> 0.85388453 | C39: =C37/C47 -> 0.92802966 | D39: =D37/D47 -> 0.90822721 | E39: AGENT | F39: Net operating invested capital / total net invested capital | G39: Core share of total net invested capital.
A40: Core contribution to Net ROI | B40: =B38*B39 -> 0.26995723 | C40: =C38*C39 -> 0.21270858 | D40: =D38*D39 -> 0.16191631 | E40: AGENT | F40: Core return × core capital weight | G40: Weighted core contribution.
A41: Non-core operating income | B41: ='Reformulated IS'!B21 -> -21 | C41: ='Reformulated IS'!C21 -> -42 | D41: ='Reformulated IS'!D21 -> -2 | E41: CHECK | F41: Reformulated IS — Non-core Operating Income | G41: Recurring non-core operating numerator.
A42: Non-operating assets | B42: ='Managerial BS'!B46 -> 820 | C42: ='Managerial BS'!C46 -> 427 | D42: ='Managerial BS'!D46 -> 454 | E42: CHECK | F42: Managerial BS — Non-operating assets | G42: Closing non-operating asset pool.
A43: Non-core return on non-operating assets | B43: =IF(B42=0,"",B41/B42) -> -0.025609756 | C43: =IF(C42=0,"",C41/C42) -> -0.098360656 | D43: =IF(D42=0,"",D41/D42) -> -0.0044052863 | E43: AGENT | F43: Non-core operating income / non-operating assets | G43: Return on non-operating assets.
A44: Non-core capital weight | B44: =B42/B47 -> 0.14611547 | C44: =C42/C47 -> 0.071970335 | D44: =D42/D47 -> 0.091772792 | E44: AGENT | F44: Non-operating assets / total net invested capital | G44: Non-core share of total net invested capital.
A45: Non-core contribution to Net ROI | B45: =B43*B44 -> -0.0037419815 | C45: =C43*C44 -> -0.0070790494 | D45: =D43*D44 -> -0.00040428543 | E45: AGENT | F45: Non-core return × non-core capital weight | G45: Weighted non-core contribution.
A46: Operating income | B46: ='Reformulated IS'!B22 -> 1494 | C46: ='Reformulated IS'!C22 -> 1220 | D46: ='Reformulated IS'!D22 -> 799 | E46: CHECK | F46: Reformulated IS — Operating Income | G46: Core + non-core operating income.
A47: Total net invested capital | B47: ='Managerial BS'!B48 -> 5612 | C47: ='Managerial BS'!C48 -> 5933 | D47: ='Managerial BS'!D48 -> 4947 | E47: CHECK | F47: Managerial BS — Total net invested capital | G47: Net operating invested capital + non-operating assets.
A48: Net ROI — direct | B48: =B46/B47 -> 0.26621525 | C48: =C46/C47 -> 0.20562953 | D48: =D46/D47 -> 0.16151203 | E48: AGENT | F48: Operating income / total net invested capital | G48: Principal Net ROI.
A49: Net ROI — decomposed | B49: =B40+B45 -> 0.26621525 | C49: =C40+C45 -> 0.20562953 | D49: =D40+D45 -> 0.16151203 | E49: AGENT | F49: Core contribution + non-core contribution | G49: Required weighted decomposition.
A50: Decomposition check | B50: =B49-B48 -> 0 | C50: =C49-C48 -> 0 | D50: =D49-D48 -> 0 | E50: AGENT | F50: Decomposed Net ROI − direct Net ROI | G50: Technical tolerance: 0.01 pp.
A51: Capital weights total | B51: =B39+B44 -> 1 | C51: =C39+C44 -> 1 | D51: =D39+D44 -> 1 | E51: AGENT | F51: Core capital weight + non-core capital weight | G51: Must equal 100%.
A52: Capital weights check | B52: =B51-1 -> 0 | C52: =C51-1 -> 0 | D52: =D51-1 -> 0 | E52: AGENT | F52: Capital weights total − 100% | G52: Technical tolerance: 0.01 pp.
A54: CORE NET RETURN DECOMPOSITION
A55: Measure / input | B55: 2025 | C55: 2024 Restated | D55: 2023 As reported | E55: Status | F55: Source / calculation | G55: Notes
A56: Sales | B56: ='Reformulated IS'!B7 -> 9935 | C56: ='Reformulated IS'!C7 -> 7715 | D56: ='Reformulated IS'!D7 -> 7176 | E56: CHECK | F56: Reformulated IS — Sales | G56: Recurring sales numerator.
A57: Core operating income | B57: ='Reformulated IS'!B18 -> 1515 | C57: ='Reformulated IS'!C18 -> 1262 | D57: ='Reformulated IS'!D18 -> 801 | E57: CHECK | F57: Reformulated IS — Core Operating Income | G57: Recurring core operating numerator.
A58: Gross operating invested capital | B58: ='Managerial BS'!B39 -> 12900 | C58: ='Managerial BS'!C39 -> 12033 | D58: ='Managerial BS'!D39 -> 9807 | E58: CHECK | F58: Managerial BS — Gross operating invested capital | G58: Closing gross operating capital.
A59: Net operating invested capital | B59: ='Managerial BS'!B40 -> 4792 | C59: ='Managerial BS'!C40 -> 5506 | D59: ='Managerial BS'!D40 -> 4493 | E59: CHECK | F59: Managerial BS — Net operating invested capital | G59: Closing net operating capital.
A60: Operating liabilities | B60: ='Managerial BS'!B29 -> 8108 | C60: ='Managerial BS'!C29 -> 6527 | D60: ='Managerial BS'!D29 -> 5314 | E60: CHECK | F60: Managerial BS — Operating liabilities | G60: Recurring operating liabilities.
A61: Core return on sales | B61: =B57/B56 -> 0.15249119 | C61: =C57/C56 -> 0.16357745 | D61: =D57/D56 -> 0.11162207 | E61: AGENT | F61: Core operating income / sales | G61: Core return on sales.
A62: Operating turnover = sales / gross operating invested capital | B62: =B56/B58 -> 0.77015504 | C62: =C56/C58 -> 0.64115349 | D62: =D56/D58 -> 0.73172224 | E62: AGENT | F62: Sales / gross operating invested capital | G62: Operating asset turnover.
A63: Operating-liability leverage = gross / net operating invested capital | B63: =B58/B59 -> 2.6919866 | C63: =C58/C59 -> 2.1854341 | D63: =D58/D59 -> 2.1827287 | E63: AGENT | F63: Gross operating invested capital / net operating invested capital | G63: Operating-liability leverage.
A64: Core net return — decomposed | B64: =B61*B62*B63 -> 0.31615192 | C64: =C61*C62*C63 -> 0.2292045 | D64: =D61*D62*D63 -> 0.17827732 | E64: AGENT | F64: Core ROS × operating turnover × operating-liability leverage | G64: Required core net return decomposition.
A65: Core net return — direct | B65: =B57/B59 -> 0.31615192 | C65: =C57/C59 -> 0.2292045 | D65: =D57/D59 -> 0.17827732 | E65: AGENT | F65: Core operating income / net operating invested capital | G65: Direct core net return.
A66: Decomposition check | B66: =B64-B65 -> 0 | C66: =C64-C65 -> 0 | D66: =D64-D65 -> 0 | E66: AGENT | F66: Decomposed core net return − direct core net return | G66: Technical tolerance: 0.01 pp.
A67: Operating liabilities / gross operating invested capital | B67: =B60/B58 -> 0.62852713 | C67: =C60/C58 -> 0.542425 | D67: =D60/D58 -> 0.54185786 | E67: AGENT | F67: Operating liabilities / gross operating invested capital | G67: Operating-liability funding share.
A68: Leverage identity = 1 / (1 − operating liabilities / gross operating invested capital) | B68: =1/(1-B67) -> 2.6919866 | C68: =1/(1-C67) -> 2.1854341 | D68: =1/(1-D67) -> 2.1827287 | E68: AGENT | F68: 1 / (1 − operating-liability ratio) | G68: Valid because net operating invested capital = gross operating invested capital − operating liabilities.
A69: Leverage identity check | B69: =B68-B63 -> 0 | C69: =C68-C63 -> 0 | D69: =D68-D63 -> 0 | E69: AGENT | F69: Leverage identity − direct gross/net leverage | G69: Should be zero.
A70: Net operating invested capital / gross operating invested capital | B70: =B59/B58 -> 0.37147287 | C70: =C59/C58 -> 0.457575 | D70: =D59/D58 -> 0.45814214 | E70: AGENT | F70: Net operating invested capital / gross operating invested capital | G70: Sensitivity denominator ratio.
A71: Denominator sensitivity status | B71: =IF(ABS(B70)<0.05,"FLAG","NO FLAG") -> NO FLAG | C71: =IF(ABS(C70)<0.05,"FLAG","NO FLAG") -> NO FLAG | D71: =IF(ABS(D70)<0.05,"FLAG","NO FLAG") -> NO FLAG | E71: AGENT | F71: Technical sensitivity test: |net operating invested capital| / gross operating invested capital < 5% | G71: FLAG only when below 5%; all periods use closing balances.
